flask_shell_ipython.py
flask_shell_ipython-0.5.2.dist-info/METADATA
flask_shell_ipython-0.5.2.dist-info/WHEEL
flask_shell_ipython-0.5.2.dist-info/entry_points.txt
flask_shell_ipython-0.5.2.dist-info/licenses/LICENSE
flask_shell_ipython-0.5.2.dist-info/RECORD
