Metadata-Version: 2.3
Name: flask-shell-ipython
Version: 0.5.2
Summary: Replace default `flask shell` command by similar command running IPython.
Project-URL: Homepage, https://github.com/ei-grad/flask-shell-ipython
Author-email: Andrew Grigorev <andrew@ei-grad.ru>
License-Expression: MIT
License-File: LICENSE
Classifier: Development Status :: 5 - Production/Stable
Classifier: Environment :: Console
Classifier: Framework :: Flask
Classifier: Framework :: IPython
Classifier: Intended Audience :: Developers
Classifier: Programming Language :: Python :: 3
Requires-Python: <4.0,>=3.8
Requires-Dist: click
Requires-Dist: flask>=1.0
Requires-Dist: ipython>=5.0.0
